polars_subclasses/__init__.py
polars_subclasses/lib.py
polars_subclasses/py.typed
dycw_polars_subclasses-0.2.0.dist-info/METADATA
dycw_polars_subclasses-0.2.0.dist-info/WHEEL
dycw_polars_subclasses-0.2.0.dist-info/RECORD
