Metadata-Version: 2.4
Name: dycw-polars-subclasses
Version: 0.2.0
Author-email: Derek Wan <d.wan@icloud.com>
Requires-Python: >=3.12
Requires-Dist: polars>=1.31.0
